thepalette/__init__.py
thepalette/colors/__init__.py
thepalette/colors/color.py
thepalette/tools/__init__.py
thepalette/tools/maker.py
thepalette-0.2.0.dist-info/licenses/LICENSE
thepalette-0.2.0.dist-info/METADATA
thepalette-0.2.0.dist-info/WHEEL
thepalette-0.2.0.dist-info/top_level.txt
thepalette-0.2.0.dist-info/RECORD
