Metadata-Version: 2.4
Name: thepalette
Version: 0.2.0
Summary: A Color Palette...
Author-email: Mohammad Parsa Mortazavi <mpmms@proton.me>
Project-URL: Homepage, https://github.com/mpmms/thepalette
Project-URL: Issues, https://github.com/mpmms/thepalette/issues
Classifier: Programming Language :: Python :: 3
Classifier: License :: OSI Approved :: MIT License
Classifier: Operating System :: OS Independent
Requires-Python: >=3.8
License-File: LICENSE
Dynamic: license-file
